incra/__init__.py
incra/main.py
incra/net.py
incra-0.1.6.dist-info/licenses/LICENSE
incra-0.1.6.dist-info/METADATA
incra-0.1.6.dist-info/WHEEL
incra-0.1.6.dist-info/top_level.txt
incra-0.1.6.dist-info/RECORD
