Metadata-Version: 2.4
Name: incra
Version: 0.1.6
Summary: Obtem dados do INCRA usando python!
Requires-Python: >=3.11
License-File: LICENSE
Requires-Dist: geopandas>=1.1.1
Requires-Dist: requests>=2.32.5
Requires-Dist: urllib3>=2.5.0
Dynamic: license-file
